ChatbotLibrary/__init__.py
ChatbotLibrary/chatbot.py
ChatbotLibrary/decision_engine.py
ChatbotLibrary/nlp_utils.py
ChatbotLibrary/utils.py
my_chatbot_lib-0.1.0.dist-info/METADATA
my_chatbot_lib-0.1.0.dist-info/WHEEL
my_chatbot_lib-0.1.0.dist-info/top_level.txt
my_chatbot_lib-0.1.0.dist-info/RECORD
