Metadata-Version: 2.1
Name: my-chatbot-lib
Version: 0.1.0
Summary: A chatbot library
Home-page: https://github.com/Evasas12/Chabot
Author: BSCS 4-5
Author-email: chuasweet11@gmail.com
License: MIT
Keywords: chatbot library NLP
Platform: UNKNOWN
Classifier: Development Status :: 3 - Alpha
Classifier: Intended Audience :: Developers
Classifier: Topic :: Software Development :: Libraries
Classifier: License :: OSI Approved :: MIT License
Classifier: Programming Language :: Python :: 3
Classifier: Programming Language :: Python :: 3.6
Classifier: Programming Language :: Python :: 3.7
Classifier: Programming Language :: Python :: 3.8
Classifier: Programming Language :: Python :: 3.9
Requires-Python: >=3.6
Requires-Dist: Flask
Requires-Dist: experta
Requires-Dist: nltk
Requires-Dist: scikit-learn
Requires-Dist: pymongo
